agents_on_langchain/__init__.py
agents_on_langchain/base_agent.py
agents_on_langchain/system_status.py
agents_on_langchain-0.1.1.dist-info/LICENSE
agents_on_langchain-0.1.1.dist-info/METADATA
agents_on_langchain-0.1.1.dist-info/WHEEL
agents_on_langchain-0.1.1.dist-info/top_level.txt
agents_on_langchain-0.1.1.dist-info/RECORD
