Metadata-Version: 2.2
Name: agents_on_langchain
Version: 0.1.1
Summary: A lightweight Python package for creating agents on Langchain for Agentic platforms
Author-email: Sinan Ozel <coding@sinan.slmail.me>
License: MIT License
Project-URL: Homepage, https://github.com/sinan-ozel/agents-on-langchain
Project-URL: Issues, https://github.com/sinan-ozel/agents-on-langchain/issues
Classifier: Programming Language :: Python :: 3
Classifier: License :: OSI Approved :: MIT License
Classifier: Operating System :: OS Independent
License-File: LICENSE
Requires-Dist: langchain-core>=0.3.31
Requires-Dist: torch>=2.4.1
Requires-Dist: typing-extensions>=4.0.0
Requires-Dist: numpy>=1.26.4
Provides-Extra: test
Requires-Dist: pytest>=7.0.0; extra == "test"
Requires-Dist: pytest-cov>=3.0.0; extra == "test"
Requires-Dist: pytest-mock>=3.14.0; extra == "test"
Provides-Extra: dev
Requires-Dist: pytest>=7.0.0; extra == "dev"
Requires-Dist: pytest-cov>=3.0.0; extra == "dev"
Requires-Dist: pytest-mock>=3.14.0; extra == "dev"
Requires-Dist: flake8>=5.0.0; extra == "dev"
Requires-Dist: black>=23.0; extra == "dev"
Requires-Dist: mypy>=1.0.0; extra == "dev"
